uart_debugger/__init__.py
uart_debugger/__main__.py
uart_debugger/cli.py
uart_debugger/parser.py
uart_debugger/uart_debugger.py
uart_debugger-0.0.3.dist-info/METADATA
uart_debugger-0.0.3.dist-info/WHEEL
uart_debugger-0.0.3.dist-info/top_level.txt
uart_debugger-0.0.3.dist-info/RECORD
